practice_1/practice_1.srcs/sources_1/new/practice.v
`timescale 1ns / 1ps

module seq_detector_1010(
    input       clk, rst_n, x,
    output      z
    );

    parameter   A = 4'h1;
    parameter   B = 4'h2;
    parameter   C = 4'h3;
    parameter   D = 4'h4;

    reg         [3:0] state, next_state;

    always @(posedge clk or negedge rst_n) begin
        if (!rst_n) begin
            state <= A;
        end else state <= next_state;
    end

    always @(state or x) begin
        case (state)
            A: begin
                if(x == 0)  next_state = A;
                else        next_state = B;
            end 
            B: begin
                if(x == 0)  next_state = C;
                else        next_state = B;
            end 
            C: begin
                if(x == 0)  next_state = A;
                else        next_state = D;
            end 
            D: begin // This state only differs when
                if(x == 0)  next_state = A;
                else        next_state = B;
            end 
            default: next_state = A;
        endcase
    end

    assign z = (state == D) && (x == 0)? 1:0;
endmodule

practice_1/practice_1.srcs/sim_1/new/tb.v
`timescale 1ns / 1ps

// module blk();
//     reg     clk, a, b;

//     initial begin
//         a = 0;
//         b = 1;
//         clk = 0;
//     end

//     always
//         clk = #5 ~clk;
    
//     always @(posedge clk) begin
//         a = b; // a = 1
//         b = a; // b = a = 1
//     end
// endmodule

// module non_blk ();
//     reg     clk, a, b;

//     initial begin
//         a = 0;
//         b = 1;
//         clk = 0;
//     end

//     always
//         clk = #5 ~clk;

//     always @(posedge clk) begin
//         a <= b;
//         b <= a;
//     end
// endmodule

`timescale 1ns/1ps
module TB;
  reg clk, rst_n, x;
  wire z;
  
  seq_detector_1010 sd(clk, rst_n, x, z);
  initial clk = 0;   
  always #2 clk = ~clk;
    
  initial begin
    x = 0;
    #1 rst_n = 0;
    #2 rst_n = 1;
    
    #3 x = 1;
    #4 x = 1;
    #4 x = 0;
    #4 x = 1;
    #4 x = 0;
    #4 x = 1;
    #4 x = 0;
    #4 x = 1;
    #4 x = 1;
    #4 x = 1;
    #4 x = 0;
    #4 x = 1;
    #4 x = 0;
    #4 x = 1;
    #4 x = 0;
    #10;
    $finish;
  end
  
  initial begin
    // Dump waves
    $dumpfile("dump.vcd");
    $dumpvars(0);
  end
endmodule

practice_1/practice_1.sim/sim_1/behav/xsim/dump.vcd
$date
   Mon Mar 10 11:03:10 2025
$end
$version
  2020.2
$end
$timescale
  1ps
$end
$scope module TB $end
$var reg 1 ! clk $end
$var reg 1 " rst_n $end
$var reg 1 # x $end
$var wire 1 $ z $end
$scope module sd $end
$var wire 1 % clk $end
$var wire 1 & rst_n $end
$var wire 1 ' x $end
$var wire 1 $ z $end
$var reg 4 ( state [3:0] $end
$var reg 4 ) next_state [3:0] $end
$var parameter 4 * A [3:0] $end
$var parameter 4 + B [3:0] $end
$var parameter 4 , C [3:0] $end
$var parameter 4 - D [3:0] $end
$upscope $end
$upscope $end
$enddefinitions $end
#0
$dumpvars
0!
x"
0#
x$
0%
x&
0'
bx (
b1 )
b1 *
b10 +
b11 ,
b100 -
$end
#1000
0"
0$
0&
b1 (
b1 )
#2000
1!
1%
b1 (
#3000
1"
1&
#4000
0!
0%
#6000
1!
1#
0$
1%
1'
b10 (
b10 )
#8000
0!
0%
#10000
1!
1%
b10 (
#12000
0!
0%
#14000
1!
0#
0$
1%
0'
b11 (
b1 )
#16000
0!
0%
#18000
1!
1#
0$
1%
1'
b100 (
b10 )
#20000
0!
0%
#22000
1!
0#
0$
1%
0'
b1 (
b1 )
#24000
0!
0%
#26000
1!
1#
0$
1%
1'
b10 (
b10 )
#28000
0!
0%
#30000
1!
0#
0$
1%
0'
b11 (
b1 )
#32000
0!
0%
#34000
1!
1#
0$
1%
1'
b100 (
b10 )
#36000
0!
0%
#38000
1!
0$
1%
b10 (
b10 )
#40000
0!
0%
#42000
1!
1%
b10 (
#44000
0!
0%
#46000
1!
0#
0$
1%
0'
b11 (
b1 )
#48000
0!
0%
#50000
1!
1#
0$
1%
1'
b100 (
b10 )
#52000
0!
0%
#54000
1!
0#
0$
1%
0'
b1 (
b1 )
#56000
0!
0%
#58000
1!
1#
0$
1%
1'
b10 (
b10 )
#60000
0!
0%
#62000
1!
0#
0$
1%
0'
b11 (
b1 )
#64000
0!
0%
#66000
1!
0$
1%
b1 (
b1 )
